[
  {
    "created_at": "Wed Jun 23 19:42:43 +0000 2021",
    "id": 1407786212551803000,
    "id_str": "1407786212551802892",
    "text": "https://t.co/4faai7MBaf",
    "truncated": false,
    "entities": {
      "hashtags": [],
      "symbols": [],
      "user_mentions": [],
      "urls": [],
      "media": [
        {
          "id": 1407786201227141000,
          "id_str": "1407786201227141120",
          "indices": [
            0,
            23
          ],
          "media_url": "http://pbs.twimg.com/media/E4l2F1vXIAAHW9b.jpg",
          "media_url_https": "https://pbs.twimg.com/media/E4l2F1vXIAAHW9b.jpg",
          "url": "https://t.co/4faai7MBaf",
          "display_url": "pic.twitter.com/4faai7MBaf",
          "expanded_url": "https://twitter.com/TweetNotLoading/status/1407786212551802892/photo/1",
          "type": "photo",
          "sizes": {
            "thumb": {
              "w": 150,
              "h": 150,
              "resize": "crop"
            },
            "medium": {
              "w": 828,
              "h": 1119,
              "resize": "fit"
            },
            "small": {
              "w": 503,
              "h": 680,
              "resize": "fit"
            },
            "large": {
              "w": 828,
              "h": 1119,
              "resize": "fit"
            }
          }
        }
      ]
    },
    "extended_entities": {
      "media": [
        {
          "id": 1407786201227141000,
          "id_str": "1407786201227141120",
          "indices": [
            0,
            23
          ],
          "media_url": "http://pbs.twimg.com/media/E4l2F1vXIAAHW9b.jpg",
          "media_url_https": "https://pbs.twimg.com/media/E4l2F1vXIAAHW9b.jpg",
          "url": "https://t.co/4faai7MBaf",
          "display_url": "pic.twitter.com/4faai7MBaf",
          "expanded_url": "https://twitter.com/TweetNotLoading/status/1407786212551802892/photo/1",
          "type": "photo",
          "sizes": {
            "thumb": {
              "w": 150,
              "h": 150,
              "resize": "crop"
            },
            "medium": {
              "w": 828,
              "h": 1119,
              "resize": "fit"
            },
            "small": {
              "w": 503,
              "h": 680,
              "resize": "fit"
            },
            "large": {
              "w": 828,
              "h": 1119,
              "resize": "fit"
            }
          }
        }
      ]
    },
    "source": "<a href=\"https://mobile.twitter.com\" rel=\"nofollow\">Twitter Web App</a>",
    "in_reply_to_status_id": null,
    "in_reply_to_status_id_str": null,
    "in_reply_to_user_id": null,
    "in_reply_to_user_id_str": null,
    "in_reply_to_screen_name": null,
    "user": {
      "id": 1335296205300134000,
      "id_str": "1335296205300133889",
      "name": "Deleted Tweets",
      "screen_name": "TweetNotLoading",
      "location": "Turn on Notifications ",
      "description": "posting the most notorious deleted tweets",
      "url": null,
      "entities": {
        "description": {
          "urls": []
        }
      },
      "protected": false,
      "followers_count": 154797,
      "friends_count": 0,
      "listed_count": 110,
      "created_at": "Sat Dec 05 18:53:29 +0000 2020",
      "favourites_count": 4,
      "utc_offset": null,
      "time_zone": null,
      "geo_enabled": true,
      "verified": false,
      "statuses_count": 15,
      "lang": null,
      "contributors_enabled": false,
      "is_translator": false,
      "is_translation_enabled": false,
      "profile_background_color": "F5F8FA",
      "profile_background_image_url": null,
      "profile_background_image_url_https": null,
      "profile_background_tile": false,
      "profile_image_url": "http://pbs.twimg.com/profile_images/1407470207380115459/SxhZcgPC_normal.jpg",
      "profile_image_url_https": "https://pbs.twimg.com/profile_images/1407470207380115459/SxhZcgPC_normal.jpg",
      "profile_banner_url": "https://pbs.twimg.com/profile_banners/1335296205300133889/1624398894",
      "profile_link_color": "1DA1F2",
      "profile_sidebar_border_color": "C0DEED",
      "profile_sidebar_fill_color": "DDEEF6",
      "profile_text_color": "333333",
      "profile_use_background_image": true,
      "has_extended_profile": false,
      "default_profile": true,
      "default_profile_image": false,
      "following": false,
      "follow_request_sent": false,
      "notifications": false,
      "translator_type": "none",
      "withheld_in_countries": []
    },
    "geo": null,
    "coordinates": null,
    "place": null,
    "contributors": null,
    "is_quote_status": false,
    "retweet_count": 15961,
    "favorite_count": 184473,
    "favorited": true,
    "retweeted": false,
    "possibly_sensitive": false,
    "lang": "und"
  },
  {
    "created_at": "Wed Jun 23 17:32:30 +0000 2021",
    "id": 1407753443654074400,
    "id_str": "1407753443654074370",
    "text": "does humanity deserve anime girls?",
    "truncated": false,
    "entities": {
      "hashtags": [],
      "symbols": [],
      "user_mentions": [],
      "urls": []
    },
    "source": "<a href=\"http://twitter.com/download/iphone\" rel=\"nofollow\">Twitter for iPhone</a>",
    "in_reply_to_status_id": null,
    "in_reply_to_status_id_str": null,
    "in_reply_to_user_id": null,
    "in_reply_to_user_id_str": null,
    "in_reply_to_screen_name": null,
    "user": {
      "id": 623420437,
      "id_str": "623420437",
      "name": "Original God • THE STORY OF THE EYE July 7th",
      "screen_name": "originalg6d",
      "location": "IG: originalg6d",
      "description": "mns anime antagonist ☆ music • design • film ☆ 1/2 of The God Hand 日本語OK originalgodbooking@gmail.com",
      "url": "https://t.co/wfCy5GnNS3",
      "entities": {
        "url": {
          "urls": [
            {
              "url": "https://t.co/wfCy5GnNS3",
              "expanded_url": "http://fanlink.to/OriginalGod",
              "display_url": "fanlink.to/OriginalGod",
              "indices": [
                0,
                23
              ]
            }
          ]
        },
        "description": {
          "urls": []
        }
      },
      "protected": false,
      "followers_count": 8016,
      "friends_count": 345,
      "listed_count": 15,
      "created_at": "Sun Jul 01 04:45:31 +0000 2012",
      "favourites_count": 61722,
      "utc_offset": null,
      "time_zone": null,
      "geo_enabled": true,
      "verified": false,
      "statuses_count": 3954,
      "lang": null,
      "contributors_enabled": false,
      "is_translator": false,
      "is_translation_enabled": false,
      "profile_background_color": "082533",
      "profile_background_image_url": "http://abs.twimg.com/images/themes/theme1/bg.png",
      "profile_background_image_url_https": "https://abs.twimg.com/images/themes/theme1/bg.png",
      "profile_background_tile": true,
      "profile_image_url": "http://pbs.twimg.com/profile_images/1379424138012454913/Z-hkcYqa_normal.jpg",
      "profile_image_url_https": "https://pbs.twimg.com/profile_images/1379424138012454913/Z-hkcYqa_normal.jpg",
      "profile_banner_url": "https://pbs.twimg.com/profile_banners/623420437/1584595136",
      "profile_link_color": "C30101",
      "profile_sidebar_border_color": "FFFFFF",
      "profile_sidebar_fill_color": "DDEEF6",
      "profile_text_color": "333333",
      "profile_use_background_image": true,
      "has_extended_profile": true,
      "default_profile": false,
      "default_profile_image": false,
      "following": true,
      "follow_request_sent": false,
      "notifications": false,
      "translator_type": "none",
      "withheld_in_countries": []
    },
    "geo": null,
    "coordinates": null,
    "place": null,
    "contributors": null,
    "is_quote_status": false,
    "retweet_count": 5,
    "favorite_count": 73,
    "favorited": true,
    "retweeted": false,
    "lang": "en"
  },
  {
    "created_at": "Wed Jun 23 16:19:03 +0000 2021",
    "id": 1407734959301877800,
    "id_str": "1407734959301877761",
    "text": "oh my god! https://t.co/Ki0VNXctGl",
    "truncated": false,
    "entities": {
      "hashtags": [],
      "symbols": [],
      "user_mentions": [],
      "urls": [],
      "media": [
        {
          "id": 1407734950191898600,
          "id_str": "1407734950191898624",
          "indices": [
            11,
            34
          ],
          "media_url": "http://pbs.twimg.com/media/E4lHeowXIAAAP48.jpg",
          "media_url_https": "https://pbs.twimg.com/media/E4lHeowXIAAAP48.jpg",
          "url": "https://t.co/Ki0VNXctGl",
          "display_url": "pic.twitter.com/Ki0VNXctGl",
          "expanded_url": "https://twitter.com/elevenpyres/status/1407734959301877761/photo/1",
          "type": "photo",
          "sizes": {
            "thumb": {
              "w": 150,
              "h": 150,
              "resize": "crop"
            },
            "large": {
              "w": 1639,
              "h": 2048,
              "resize": "fit"
            },
            "small": {
              "w": 544,
              "h": 680,
              "resize": "fit"
            },
            "medium": {
              "w": 960,
              "h": 1200,
              "resize": "fit"
            }
          }
        }
      ]
    },
    "extended_entities": {
      "media": [
        {
          "id": 1407734950191898600,
          "id_str": "1407734950191898624",
          "indices": [
            11,
            34
          ],
          "media_url": "http://pbs.twimg.com/media/E4lHeowXIAAAP48.jpg",
          "media_url_https": "https://pbs.twimg.com/media/E4lHeowXIAAAP48.jpg",
          "url": "https://t.co/Ki0VNXctGl",
          "display_url": "pic.twitter.com/Ki0VNXctGl",
          "expanded_url": "https://twitter.com/elevenpyres/status/1407734959301877761/photo/1",
          "type": "photo",
          "sizes": {
            "thumb": {
              "w": 150,
              "h": 150,
              "resize": "crop"
            },
            "large": {
              "w": 1639,
              "h": 2048,
              "resize": "fit"
            },
            "small": {
              "w": 544,
              "h": 680,
              "resize": "fit"
            },
            "medium": {
              "w": 960,
              "h": 1200,
              "resize": "fit"
            }
          }
        },
        {
          "id": 1407734951198531600,
          "id_str": "1407734951198531590",
          "indices": [
            11,
            34
          ],
          "media_url": "http://pbs.twimg.com/media/E4lHesgXIAYl-7z.jpg",
          "media_url_https": "https://pbs.twimg.com/media/E4lHesgXIAYl-7z.jpg",
          "url": "https://t.co/Ki0VNXctGl",
          "display_url": "pic.twitter.com/Ki0VNXctGl",
          "expanded_url": "https://twitter.com/elevenpyres/status/1407734959301877761/photo/1",
          "type": "photo",
          "sizes": {
            "thumb": {
              "w": 150,
              "h": 150,
              "resize": "crop"
            },
            "large": {
              "w": 1638,
              "h": 2048,
              "resize": "fit"
            },
            "medium": {
              "w": 960,
              "h": 1200,
              "resize": "fit"
            },
            "small": {
              "w": 544,
              "h": 680,
              "resize": "fit"
            }
          }
        },
        {
          "id": 1407734952955977700,
          "id_str": "1407734952955977732",
          "indices": [
            11,
            34
          ],
          "media_url": "http://pbs.twimg.com/media/E4lHezDXoAQfaLX.jpg",
          "media_url_https": "https://pbs.twimg.com/media/E4lHezDXoAQfaLX.jpg",
          "url": "https://t.co/Ki0VNXctGl",
          "display_url": "pic.twitter.com/Ki0VNXctGl",
          "expanded_url": "https://twitter.com/elevenpyres/status/1407734959301877761/photo/1",
          "type": "photo",
          "sizes": {
            "thumb": {
              "w": 150,
              "h": 150,
              "resize": "crop"
            },
            "medium": {
              "w": 960,
              "h": 1200,
              "resize": "fit"
            },
            "small": {
              "w": 544,
              "h": 680,
              "resize": "fit"
            },
            "large": {
              "w": 1638,
              "h": 2048,
              "resize": "fit"
            }
          }
        }
      ]
    },
    "source": "<a href=\"http://twitter.com/download/iphone\" rel=\"nofollow\">Twitter for iPhone</a>",
    "in_reply_to_status_id": null,
    "in_reply_to_status_id_str": null,
    "in_reply_to_user_id": null,
    "in_reply_to_user_id_str": null,
    "in_reply_to_screen_name": null,
    "user": {
      "id": 1188486902279790600,
      "id_str": "1188486902279790592",
      "name": "unit-11",
      "screen_name": "elevenpyres",
      "location": "nyc",
      "description": "my name is Eleven, they/them ★ https://t.co/jkkVFu7oPb ★ https://t.co/U8ej2kFCOL",
      "url": "https://t.co/iSqYkP71uF",
      "entities": {
        "url": {
          "urls": [
            {
              "url": "https://t.co/iSqYkP71uF",
              "expanded_url": "https://artistsourced.com/collections/eleven-pyres",
              "display_url": "artistsourced.com/collections/el…",
              "indices": [
                0,
                23
              ]
            }
          ]
        },
        "description": {
          "urls": [
            {
              "url": "https://t.co/jkkVFu7oPb",
              "expanded_url": "http://twitch.tv/elevenpyres",
              "display_url": "twitch.tv/elevenpyres",
              "indices": [
                31,
                54
              ]
            },
            {
              "url": "https://t.co/U8ej2kFCOL",
              "expanded_url": "http://instagram.com/deadanimemom",
              "display_url": "instagram.com/deadanimemom",
              "indices": [
                57,
                80
              ]
            }
          ]
        }
      },
      "protected": false,
      "followers_count": 14713,
      "friends_count": 378,
      "listed_count": 20,
      "created_at": "Sun Oct 27 16:07:34 +0000 2019",
      "favourites_count": 40120,
      "utc_offset": null,
      "time_zone": null,
      "geo_enabled": false,
      "verified": false,
      "statuses_count": 6358,
      "lang": null,
      "contributors_enabled": false,
      "is_translator": false,
      "is_translation_enabled": false,
      "profile_background_color": "F5F8FA",
      "profile_background_image_url": null,
      "profile_background_image_url_https": null,
      "profile_background_tile": false,
      "profile_image_url": "http://pbs.twimg.com/profile_images/1303104807369166848/7DSbgyR3_normal.jpg",
      "profile_image_url_https": "https://pbs.twimg.com/profile_images/1303104807369166848/7DSbgyR3_normal.jpg",
      "profile_banner_url": "https://pbs.twimg.com/profile_banners/1188486902279790592/1620180906",
      "profile_link_color": "1DA1F2",
      "profile_sidebar_border_color": "C0DEED",
      "profile_sidebar_fill_color": "DDEEF6",
      "profile_text_color": "333333",
      "profile_use_background_image": true,
      "has_extended_profile": true,
      "default_profile": true,
      "default_profile_image": false,
      "following": false,
      "follow_request_sent": false,
      "notifications": false,
      "translator_type": "none",
      "withheld_in_countries": []
    },
    "geo": null,
    "coordinates": null,
    "place": null,
    "contributors": null,
    "is_quote_status": false,
    "retweet_count": 2462,
    "favorite_count": 16761,
    "favorited": true,
    "retweeted": false,
    "possibly_sensitive": false,
    "lang": "en"
  },
  {
    "created_at": "Wed Jun 23 16:04:17 +0000 2021",
    "id": 1407731244469731300,
    "id_str": "1407731244469731333",
    "text": "https://t.co/e3g6nRkI4t",
    "truncated": false,
    "entities": {
      "hashtags": [],
      "symbols": [],
      "user_mentions": [],
      "urls": [],
      "media": [
        {
          "id": 1407731232528552000,
          "id_str": "1407731232528551943",
          "indices": [
            0,
            23
          ],
          "media_url": "http://pbs.twimg.com/media/E4lEGPYWUAcKrMF.jpg",
          "media_url_https": "https://pbs.twimg.com/media/E4lEGPYWUAcKrMF.jpg",
          "url": "https://t.co/e3g6nRkI4t",
          "display_url": "pic.twitter.com/e3g6nRkI4t",
          "expanded_url": "https://twitter.com/TweetNotLoading/status/1407731244469731333/photo/1",
          "type": "photo",
          "sizes": {
            "large": {
              "w": 473,
              "h": 1024,
              "resize": "fit"
            },
            "thumb": {
              "w": 150,
              "h": 150,
              "resize": "crop"
            },
            "small": {
              "w": 314,
              "h": 680,
              "resize": "fit"
            },
            "medium": {
              "w": 473,
              "h": 1024,
              "resize": "fit"
            }
          }
        }
      ]
    },
    "extended_entities": {
      "media": [
        {
          "id": 1407731232528552000,
          "id_str": "1407731232528551943",
          "indices": [
            0,
            23
          ],
          "media_url": "http://pbs.twimg.com/media/E4lEGPYWUAcKrMF.jpg",
          "media_url_https": "https://pbs.twimg.com/media/E4lEGPYWUAcKrMF.jpg",
          "url": "https://t.co/e3g6nRkI4t",
          "display_url": "pic.twitter.com/e3g6nRkI4t",
          "expanded_url": "https://twitter.com/TweetNotLoading/status/1407731244469731333/photo/1",
          "type": "photo",
          "sizes": {
            "large": {
              "w": 473,
              "h": 1024,
              "resize": "fit"
            },
            "thumb": {
              "w": 150,
              "h": 150,
              "resize": "crop"
            },
            "small": {
              "w": 314,
              "h": 680,
              "resize": "fit"
            },
            "medium": {
              "w": 473,
              "h": 1024,
              "resize": "fit"
            }
          }
        }
      ]
    },
    "source": "<a href=\"https://mobile.twitter.com\" rel=\"nofollow\">Twitter Web App</a>",
    "in_reply_to_status_id": null,
    "in_reply_to_status_id_str": null,
    "in_reply_to_user_id": null,
    "in_reply_to_user_id_str": null,
    "in_reply_to_screen_name": null,
    "user": {
      "id": 1335296205300134000,
      "id_str": "1335296205300133889",
      "name": "Deleted Tweets",
      "screen_name": "TweetNotLoading",
      "location": "Turn on Notifications ",
      "description": "posting the most notorious deleted tweets",
      "url": null,
      "entities": {
        "description": {
          "urls": []
        }
      },
      "protected": false,
      "followers_count": 154797,
      "friends_count": 0,
      "listed_count": 110,
      "created_at": "Sat Dec 05 18:53:29 +0000 2020",
      "favourites_count": 4,
      "utc_offset": null,
      "time_zone": null,
      "geo_enabled": true,
      "verified": false,
      "statuses_count": 15,
      "lang": null,
      "contributors_enabled": false,
      "is_translator": false,
      "is_translation_enabled": false,
      "profile_background_color": "F5F8FA",
      "profile_background_image_url": null,
      "profile_background_image_url_https": null,
      "profile_background_tile": false,
      "profile_image_url": "http://pbs.twimg.com/profile_images/1407470207380115459/SxhZcgPC_normal.jpg",
      "profile_image_url_https": "https://pbs.twimg.com/profile_images/1407470207380115459/SxhZcgPC_normal.jpg",
      "profile_banner_url": "https://pbs.twimg.com/profile_banners/1335296205300133889/1624398894",
      "profile_link_color": "1DA1F2",
      "profile_sidebar_border_color": "C0DEED",
      "profile_sidebar_fill_color": "DDEEF6",
      "profile_text_color": "333333",
      "profile_use_background_image": true,
      "has_extended_profile": false,
      "default_profile": true,
      "default_profile_image": false,
      "following": false,
      "follow_request_sent": false,
      "notifications": false,
      "translator_type": "none",
      "withheld_in_countries": []
    },
    "geo": null,
    "coordinates": null,
    "place": null,
    "contributors": null,
    "is_quote_status": false,
    "retweet_count": 15117,
    "favorite_count": 200228,
    "favorited": true,
    "retweeted": false,
    "possibly_sensitive": false,
    "lang": "und"
  },
  {
    "created_at": "Wed Jun 23 13:15:24 +0000 2021",
    "id": 1407688743276929000,
    "id_str": "1407688743276929029",
    "text": "It's just an anime, it can't hurt you The anime :\n\nThe anime : https://t.co/vZvsGqkgxd",
    "truncated": false,
    "entities": {
      "hashtags": [],
      "symbols": [],
      "user_mentions": [],
      "urls": [],
      "media": [
        {
          "id": 1407688737501372400,
          "id_str": "1407688737501372416",
          "indices": [
            63,
            86
          ],
          "media_url": "http://pbs.twimg.com/media/E4kdctEWYAAPB71.jpg",
          "media_url_https": "https://pbs.twimg.com/media/E4kdctEWYAAPB71.jpg",
          "url": "https://t.co/vZvsGqkgxd",
          "display_url": "pic.twitter.com/vZvsGqkgxd",
          "expanded_url": "https://twitter.com/GhibliAccount/status/1407688743276929029/photo/1",
          "type": "photo",
          "sizes": {
            "thumb": {
              "w": 150,
              "h": 150,
              "resize": "crop"
            },
            "small": {
              "w": 680,
              "h": 365,
              "resize": "fit"
            },
            "medium": {
              "w": 1199,
              "h": 643,
              "resize": "fit"
            },
            "large": {
              "w": 1199,
              "h": 643,
              "resize": "fit"
            }
          }
        }
      ]
    },
    "extended_entities": {
      "media": [
        {
          "id": 1407688737501372400,
          "id_str": "1407688737501372416",
          "indices": [
            63,
            86
          ],
          "media_url": "http://pbs.twimg.com/media/E4kdctEWYAAPB71.jpg",
          "media_url_https": "https://pbs.twimg.com/media/E4kdctEWYAAPB71.jpg",
          "url": "https://t.co/vZvsGqkgxd",
          "display_url": "pic.twitter.com/vZvsGqkgxd",
          "expanded_url": "https://twitter.com/GhibliAccount/status/1407688743276929029/photo/1",
          "type": "photo",
          "sizes": {
            "thumb": {
              "w": 150,
              "h": 150,
              "resize": "crop"
            },
            "small": {
              "w": 680,
              "h": 365,
              "resize": "fit"
            },
            "medium": {
              "w": 1199,
              "h": 643,
              "resize": "fit"
            },
            "large": {
              "w": 1199,
              "h": 643,
              "resize": "fit"
            }
          }
        }
      ]
    },
    "source": "<a href=\"https://mobile.twitter.com\" rel=\"nofollow\">Twitter Web App</a>",
    "in_reply_to_status_id": null,
    "in_reply_to_status_id_str": null,
    "in_reply_to_user_id": null,
    "in_reply_to_user_id_str": null,
    "in_reply_to_screen_name": null,
    "user": {
      "id": 992732471455371300,
      "id_str": "992732471455371265",
      "name": "Studio Ghibli",
      "screen_name": "GhibliAccount",
      "location": "Goro ✣",
      "description": ".                      Studio Ghibli (スタジオジリ)                       .  \n                                Aesthetic account",
      "url": null,
      "entities": {
        "description": {
          "urls": []
        }
      },
      "protected": false,
      "followers_count": 48311,
      "friends_count": 67,
      "listed_count": 193,
      "created_at": "Sat May 05 11:47:20 +0000 2018",
      "favourites_count": 15929,
      "utc_offset": null,
      "time_zone": null,
      "geo_enabled": false,
      "verified": false,
      "statuses_count": 1039,
      "lang": null,
      "contributors_enabled": false,
      "is_translator": false,
      "is_translation_enabled": false,
      "profile_background_color": "000000",
      "profile_background_image_url": "http://abs.twimg.com/images/themes/theme1/bg.png",
      "profile_background_image_url_https": "https://abs.twimg.com/images/themes/theme1/bg.png",
      "profile_background_tile": false,
      "profile_image_url": "http://pbs.twimg.com/profile_images/1391530283334242318/Qq1UKaR5_normal.jpg",
      "profile_image_url_https": "https://pbs.twimg.com/profile_images/1391530283334242318/Qq1UKaR5_normal.jpg",
      "profile_banner_url": "https://pbs.twimg.com/profile_banners/992732471455371265/1620601801",
      "profile_link_color": "981CEB",
      "profile_sidebar_border_color": "000000",
      "profile_sidebar_fill_color": "000000",
      "profile_text_color": "000000",
      "profile_use_background_image": false,
      "has_extended_profile": true,
      "default_profile": false,
      "default_profile_image": false,
      "following": false,
      "follow_request_sent": false,
      "notifications": false,
      "translator_type": "none",
      "withheld_in_countries": []
    },
    "geo": null,
    "coordinates": null,
    "place": null,
    "contributors": null,
    "is_quote_status": false,
    "retweet_count": 5893,
    "favorite_count": 30451,
    "favorited": true,
    "retweeted": false,
    "possibly_sensitive": false,
    "lang": "en"
  },
  {
    "created_at": "Wed Jun 23 11:41:37 +0000 2021",
    "id": 1407665140099547100,
    "id_str": "1407665140099547142",
    "text": "a guy who pays women to tell him his design suck shit",
    "truncated": false,
    "entities": {
      "hashtags": [],
      "symbols": [],
      "user_mentions": [],
      "urls": []
    },
    "source": "<a href=\"http://twitter.com/download/iphone\" rel=\"nofollow\">Twitter for iPhone</a>",
    "in_reply_to_status_id": null,
    "in_reply_to_status_id_str": null,
    "in_reply_to_user_id": null,
    "in_reply_to_user_id_str": null,
    "in_reply_to_screen_name": null,
    "user": {
      "id": 25943344,
      "id_str": "25943344",
      "name": "coolfontguy69",
      "screen_name": "w__h_",
      "location": "",
      "description": "I love fonts",
      "url": "https://t.co/8Uo5Q3HmFU",
      "entities": {
        "url": {
          "urls": [
            {
              "url": "https://t.co/8Uo5Q3HmFU",
              "expanded_url": "https://www.instagram.com/w__h____/",
              "display_url": "instagram.com/w__h____/",
              "indices": [
                0,
                23
              ]
            }
          ]
        },
        "description": {
          "urls": []
        }
      },
      "protected": false,
      "followers_count": 6199,
      "friends_count": 1434,
      "listed_count": 53,
      "created_at": "Mon Mar 23 03:18:21 +0000 2009",
      "favourites_count": 38438,
      "utc_offset": null,
      "time_zone": null,
      "geo_enabled": false,
      "verified": false,
      "statuses_count": 13570,
      "lang": null,
      "contributors_enabled": false,
      "is_translator": false,
      "is_translation_enabled": false,
      "profile_background_color": "C0DEED",
      "profile_background_image_url": "http://abs.twimg.com/images/themes/theme1/bg.png",
      "profile_background_image_url_https": "https://abs.twimg.com/images/themes/theme1/bg.png",
      "profile_background_tile": false,
      "profile_image_url": "http://pbs.twimg.com/profile_images/1409341648115363845/8-M_LM3Z_normal.jpg",
      "profile_image_url_https": "https://pbs.twimg.com/profile_images/1409341648115363845/8-M_LM3Z_normal.jpg",
      "profile_link_color": "007BFF",
      "profile_sidebar_border_color": "C0DEED",
      "profile_sidebar_fill_color": "DDEEF6",
      "profile_text_color": "333333",
      "profile_use_background_image": true,
      "has_extended_profile": false,
      "default_profile": false,
      "default_profile_image": false,
      "following": true,
      "follow_request_sent": false,
      "notifications": false,
      "translator_type": "none",
      "withheld_in_countries": []
    },
    "geo": null,
    "coordinates": null,
    "place": null,
    "contributors": null,
    "is_quote_status": false,
    "retweet_count": 3,
    "favorite_count": 44,
    "favorited": true,
    "retweeted": false,
    "lang": "en"
  },
  {
    "created_at": "Wed Jun 23 08:33:16 +0000 2021",
    "id": 1407617741230575600,
    "id_str": "1407617741230575624",
    "text": "we live in a society https://t.co/upEST2qEak",
    "truncated": false,
    "entities": {
      "hashtags": [],
      "symbols": [],
      "user_mentions": [],
      "urls": [],
      "media": [
        {
          "id": 1407617737413873700,
          "id_str": "1407617737413873664",
          "indices": [
            21,
            44
          ],
          "media_url": "http://pbs.twimg.com/media/E4jc39IX0AAaCqZ.jpg",
          "media_url_https": "https://pbs.twimg.com/media/E4jc39IX0AAaCqZ.jpg",
          "url": "https://t.co/upEST2qEak",
          "display_url": "pic.twitter.com/upEST2qEak",
          "expanded_url": "https://twitter.com/gloless3x/status/1407617741230575624/photo/1",
          "type": "photo",
          "sizes": {
            "large": {
              "w": 1241,
              "h": 1827,
              "resize": "fit"
            },
            "thumb": {
              "w": 150,
              "h": 150,
              "resize": "crop"
            },
            "medium": {
              "w": 815,
              "h": 1200,
              "resize": "fit"
            },
            "small": {
              "w": 462,
              "h": 680,
              "resize": "fit"
            }
          }
        }
      ]
    },
    "extended_entities": {
      "media": [
        {
          "id": 1407617737413873700,
          "id_str": "1407617737413873664",
          "indices": [
            21,
            44
          ],
          "media_url": "http://pbs.twimg.com/media/E4jc39IX0AAaCqZ.jpg",
          "media_url_https": "https://pbs.twimg.com/media/E4jc39IX0AAaCqZ.jpg",
          "url": "https://t.co/upEST2qEak",
          "display_url": "pic.twitter.com/upEST2qEak",
          "expanded_url": "https://twitter.com/gloless3x/status/1407617741230575624/photo/1",
          "type": "photo",
          "sizes": {
            "large": {
              "w": 1241,
              "h": 1827,
              "resize": "fit"
            },
            "thumb": {
              "w": 150,
              "h": 150,
              "resize": "crop"
            },
            "medium": {
              "w": 815,
              "h": 1200,
              "resize": "fit"
            },
            "small": {
              "w": 462,
              "h": 680,
              "resize": "fit"
            }
          }
        },
        {
          "id": 1407617737405370400,
          "id_str": "1407617737405370369",
          "indices": [
            21,
            44
          ],
          "media_url": "http://pbs.twimg.com/media/E4jc39GWEAEvNLs.jpg",
          "media_url_https": "https://pbs.twimg.com/media/E4jc39GWEAEvNLs.jpg",
          "url": "https://t.co/upEST2qEak",
          "display_url": "pic.twitter.com/upEST2qEak",
          "expanded_url": "https://twitter.com/gloless3x/status/1407617741230575624/photo/1",
          "type": "photo",
          "sizes": {
            "thumb": {
              "w": 150,
              "h": 150,
              "resize": "crop"
            },
            "small": {
              "w": 475,
              "h": 680,
              "resize": "fit"
            },
            "medium": {
              "w": 615,
              "h": 880,
              "resize": "fit"
            },
            "large": {
              "w": 615,
              "h": 880,
              "resize": "fit"
            }
          }
        }
      ]
    },
    "source": "<a href=\"http://twitter.com/download/iphone\" rel=\"nofollow\">Twitter for iPhone</a>",
    "in_reply_to_status_id": null,
    "in_reply_to_status_id_str": null,
    "in_reply_to_user_id": null,
    "in_reply_to_user_id_str": null,
    "in_reply_to_screen_name": null,
    "user": {
      "id": 999772260,
      "id_str": "999772260",
      "name": "mbg",
      "screen_name": "gloless3x",
      "location": "Detroit, MI",
      "description": "2 time rookie of the year",
      "url": null,
      "entities": {
        "description": {
          "urls": []
        }
      },
      "protected": false,
      "followers_count": 5505,
      "friends_count": 390,
      "listed_count": 70,
      "created_at": "Sun Dec 09 17:46:28 +0000 2012",
      "favourites_count": 1798,
      "utc_offset": null,
      "time_zone": null,
      "geo_enabled": true,
      "verified": false,
      "statuses_count": 161654,
      "lang": null,
      "contributors_enabled": false,
      "is_translator": false,
      "is_translation_enabled": false,
      "profile_background_color": "C0DEED",
      "profile_background_image_url": "http://abs.twimg.com/images/themes/theme1/bg.png",
      "profile_background_image_url_https": "https://abs.twimg.com/images/themes/theme1/bg.png",
      "profile_background_tile": false,
      "profile_image_url": "http://pbs.twimg.com/profile_images/1406471478082686977/0kIo8v69_normal.jpg",
      "profile_image_url_https": "https://pbs.twimg.com/profile_images/1406471478082686977/0kIo8v69_normal.jpg",
      "profile_banner_url": "https://pbs.twimg.com/profile_banners/999772260/1619877653",
      "profile_link_color": "1DA1F2",
      "profile_sidebar_border_color": "C0DEED",
      "profile_sidebar_fill_color": "DDEEF6",
      "profile_text_color": "333333",
      "profile_use_background_image": true,
      "has_extended_profile": true,
      "default_profile": true,
      "default_profile_image": false,
      "following": false,
      "follow_request_sent": false,
      "notifications": false,
      "translator_type": "none",
      "withheld_in_countries": []
    },
    "geo": null,
    "coordinates": null,
    "place": null,
    "contributors": null,
    "is_quote_status": false,
    "retweet_count": 5907,
    "favorite_count": 65590,
    "favorited": true,
    "retweeted": false,
    "possibly_sensitive": false,
    "lang": "en"
  },
  {
    "created_at": "Wed Jun 23 08:14:10 +0000 2021",
    "id": 1407612933530546200,
    "id_str": "1407612933530546181",
    "text": "i am a proud ageist",
    "truncated": false,
    "entities": {
      "hashtags": [],
      "symbols": [],
      "user_mentions": [],
      "urls": []
    },
    "source": "<a href=\"http://twitter.com/download/iphone\" rel=\"nofollow\">Twitter for iPhone</a>",
    "in_reply_to_status_id": null,
    "in_reply_to_status_id_str": null,
    "in_reply_to_user_id": null,
    "in_reply_to_user_id_str": null,
    "in_reply_to_screen_name": null,
    "user": {
      "id": 756300778277449700,
      "id_str": "756300778277449728",
      "name": "zeitgeist",
      "screen_name": "skinnnbag",
      "location": "",
      "description": "",
      "url": null,
      "entities": {
        "description": {
          "urls": []
        }
      },
      "protected": false,
      "followers_count": 46,
      "friends_count": 125,
      "listed_count": 0,
      "created_at": "Fri Jul 22 01:32:11 +0000 2016",
      "favourites_count": 3702,
      "utc_offset": null,
      "time_zone": null,
      "geo_enabled": true,
      "verified": false,
      "statuses_count": 1041,
      "lang": null,
      "contributors_enabled": false,
      "is_translator": false,
      "is_translation_enabled": false,
      "profile_background_color": "F5F8FA",
      "profile_background_image_url": null,
      "profile_background_image_url_https": null,
      "profile_background_tile": false,
      "profile_image_url": "http://pbs.twimg.com/profile_images/1407633468805193734/g0BqkT1W_normal.jpg",
      "profile_image_url_https": "https://pbs.twimg.com/profile_images/1407633468805193734/g0BqkT1W_normal.jpg",
      "profile_banner_url": "https://pbs.twimg.com/profile_banners/756300778277449728/1624440946",
      "profile_link_color": "1DA1F2",
      "profile_sidebar_border_color": "C0DEED",
      "profile_sidebar_fill_color": "DDEEF6",
      "profile_text_color": "333333",
      "profile_use_background_image": true,
      "has_extended_profile": false,
      "default_profile": true,
      "default_profile_image": false,
      "following": true,
      "follow_request_sent": false,
      "notifications": false,
      "translator_type": "none",
      "withheld_in_countries": []
    },
    "geo": null,
    "coordinates": null,
    "place": null,
    "contributors": null,
    "is_quote_status": false,
    "retweet_count": 0,
    "favorite_count": 1,
    "favorited": true,
    "retweeted": false,
    "lang": "en"
  },
  {
    "created_at": "Wed Jun 23 05:21:27 +0000 2021",
    "id": 1407569470239903700,
    "id_str": "1407569470239903746",
    "text": "i just caused a car accident i feel so horrible i’m so grateful everyone’s ok tho",
    "truncated": false,
    "entities": {
      "hashtags": [],
      "symbols": [],
      "user_mentions": [],
      "urls": []
    },
    "source": "<a href=\"http://twitter.com/download/iphone\" rel=\"nofollow\">Twitter for iPhone</a>",
    "in_reply_to_status_id": null,
    "in_reply_to_status_id_str": null,
    "in_reply_to_user_id": null,
    "in_reply_to_user_id_str": null,
    "in_reply_to_screen_name": null,
    "user": {
      "id": 1243280352874877000,
      "id_str": "1243280352874876928",
      "name": "ok",
      "screen_name": "toadcummies",
      "location": "",
      "description": "",
      "url": null,
      "entities": {
        "description": {
          "urls": []
        }
      },
      "protected": true,
      "followers_count": 21,
      "friends_count": 66,
      "listed_count": 0,
      "created_at": "Thu Mar 26 20:55:18 +0000 2020",
      "favourites_count": 590,
      "utc_offset": null,
      "time_zone": null,
      "geo_enabled": true,
      "verified": false,
      "statuses_count": 796,
      "lang": null,
      "contributors_enabled": false,
      "is_translator": false,
      "is_translation_enabled": false,
      "profile_background_color": "F5F8FA",
      "profile_background_image_url": null,
      "profile_background_image_url_https": null,
      "profile_background_tile": false,
      "profile_image_url": "http://pbs.twimg.com/profile_images/1248496488906231808/j-5Zb9_1_normal.jpg",
      "profile_image_url_https": "https://pbs.twimg.com/profile_images/1248496488906231808/j-5Zb9_1_normal.jpg",
      "profile_link_color": "1DA1F2",
      "profile_sidebar_border_color": "C0DEED",
      "profile_sidebar_fill_color": "DDEEF6",
      "profile_text_color": "333333",
      "profile_use_background_image": true,
      "has_extended_profile": true,
      "default_profile": true,
      "default_profile_image": false,
      "following": true,
      "follow_request_sent": false,
      "notifications": false,
      "translator_type": "none",
      "withheld_in_countries": []
    },
    "geo": null,
    "coordinates": null,
    "place": null,
    "contributors": null,
    "is_quote_status": false,
    "retweet_count": 0,
    "favorite_count": 2,
    "favorited": true,
    "retweeted": false,
    "lang": "en"
  },
  {
    "created_at": "Wed Jun 23 05:13:02 +0000 2021",
    "id": 1407567349343932400,
    "id_str": "1407567349343932420",
    "text": "what’s with all the old people sucking on ur nutsack",
    "truncated": false,
    "entities": {
      "hashtags": [],
      "symbols": [],
      "user_mentions": [],
      "urls": []
    },
    "source": "<a href=\"http://twitter.com/download/iphone\" rel=\"nofollow\">Twitter for iPhone</a>",
    "in_reply_to_status_id": null,
    "in_reply_to_status_id_str": null,
    "in_reply_to_user_id": null,
    "in_reply_to_user_id_str": null,
    "in_reply_to_screen_name": null,
    "user": {
      "id": 1090504233428766700,
      "id_str": "1090504233428766720",
      "name": "marisol",
      "screen_name": "lilbl00dcl0t",
      "location": "Los Angeles, CA",
      "description": "decaying from the inside out.      cuticle DESTROYER",
      "url": null,
      "entities": {
        "description": {
          "urls": []
        }
      },
      "protected": false,
      "followers_count": 45,
      "friends_count": 131,
      "listed_count": 0,
      "created_at": "Wed Jan 30 06:57:24 +0000 2019",
      "favourites_count": 571,
      "utc_offset": null,
      "time_zone": null,
      "geo_enabled": false,
      "verified": false,
      "statuses_count": 465,
      "lang": null,
      "contributors_enabled": false,
      "is_translator": false,
      "is_translation_enabled": false,
      "profile_background_color": "F5F8FA",
      "profile_background_image_url": null,
      "profile_background_image_url_https": null,
      "profile_background_tile": false,
      "profile_image_url": "http://pbs.twimg.com/profile_images/1339466043090063360/KxrnQlAy_normal.jpg",
      "profile_image_url_https": "https://pbs.twimg.com/profile_images/1339466043090063360/KxrnQlAy_normal.jpg",
      "profile_banner_url": "https://pbs.twimg.com/profile_banners/1090504233428766720/1608188450",
      "profile_link_color": "1DA1F2",
      "profile_sidebar_border_color": "C0DEED",
      "profile_sidebar_fill_color": "DDEEF6",
      "profile_text_color": "333333",
      "profile_use_background_image": true,
      "has_extended_profile": true,
      "default_profile": true,
      "default_profile_image": false,
      "following": true,
      "follow_request_sent": false,
      "notifications": false,
      "translator_type": "none",
      "withheld_in_countries": []
    },
    "geo": null,
    "coordinates": null,
    "place": null,
    "contributors": null,
    "is_quote_status": false,
    "retweet_count": 0,
    "favorite_count": 2,
    "favorited": true,
    "retweeted": false,
    "lang": "en"
  },
  {
    "created_at": "Wed Jun 23 04:45:05 +0000 2021",
    "id": 1407560318646206500,
    "id_str": "1407560318646206465",
    "text": "I ain’t do shit cause I am the shit",
    "truncated": false,
    "entities": {
      "hashtags": [],
      "symbols": [],
      "user_mentions": [],
      "urls": []
    },
    "source": "<a href=\"http://twitter.com/download/iphone\" rel=\"nofollow\">Twitter for iPhone</a>",
    "in_reply_to_status_id": null,
    "in_reply_to_status_id_str": null,
    "in_reply_to_user_id": null,
    "in_reply_to_user_id_str": null,
    "in_reply_to_screen_name": null,
    "user": {
      "id": 955275587995631600,
      "id_str": "955275587995631616",
      "name": "Queen Von",
      "screen_name": "lilpearlita",
      "location": "",
      "description": "🦹🏾‍♂️🦹🏾‍♂️🦹🏾‍♂️🦹🏾‍♂️",
      "url": null,
      "entities": {
        "description": {
          "urls": []
        }
      },
      "protected": true,
      "followers_count": 29,
      "friends_count": 46,
      "listed_count": 0,
      "created_at": "Mon Jan 22 03:07:03 +0000 2018",
      "favourites_count": 1371,
      "utc_offset": null,
      "time_zone": null,
      "geo_enabled": true,
      "verified": false,
      "statuses_count": 2120,
      "lang": null,
      "contributors_enabled": false,
      "is_translator": false,
      "is_translation_enabled": false,
      "profile_background_color": "000000",
      "profile_background_image_url": "http://abs.twimg.com/images/themes/theme1/bg.png",
      "profile_background_image_url_https": "https://abs.twimg.com/images/themes/theme1/bg.png",
      "profile_background_tile": false,
      "profile_image_url": "http://pbs.twimg.com/profile_images/1110435220702953472/R4MoGERy_normal.jpg",
      "profile_image_url_https": "https://pbs.twimg.com/profile_images/1110435220702953472/R4MoGERy_normal.jpg",
      "profile_banner_url": "https://pbs.twimg.com/profile_banners/955275587995631616/1516591339",
      "profile_link_color": "1B95E0",
      "profile_sidebar_border_color": "000000",
      "profile_sidebar_fill_color": "000000",
      "profile_text_color": "000000",
      "profile_use_background_image": false,
      "has_extended_profile": false,
      "default_profile": false,
      "default_profile_image": false,
      "following": true,
      "follow_request_sent": false,
      "notifications": false,
      "translator_type": "none",
      "withheld_in_countries": []
    },
    "geo": null,
    "coordinates": null,
    "place": null,
    "contributors": null,
    "is_quote_status": false,
    "retweet_count": 0,
    "favorite_count": 1,
    "favorited": true,
    "retweeted": false,
    "lang": "en"
  },
  {
    "created_at": "Wed Jun 23 04:28:31 +0000 2021",
    "id": 1407556149319061500,
    "id_str": "1407556149319061510",
    "text": "this is why i don’t trust ppl with blue/green eyes😒",
    "truncated": false,
    "entities": {
      "hashtags": [],
      "symbols": [],
      "user_mentions": [],
      "urls": []
    },
    "source": "<a href=\"http://twitter.com/download/iphone\" rel=\"nofollow\">Twitter for iPhone</a>",
    "in_reply_to_status_id": null,
    "in_reply_to_status_id_str": null,
    "in_reply_to_user_id": null,
    "in_reply_to_user_id_str": null,
    "in_reply_to_screen_name": null,
    "user": {
      "id": 1090504233428766700,
      "id_str": "1090504233428766720",
      "name": "marisol",
      "screen_name": "lilbl00dcl0t",
      "location": "Los Angeles, CA",
      "description": "decaying from the inside out.      cuticle DESTROYER",
      "url": null,
      "entities": {
        "description": {
          "urls": []
        }
      },
      "protected": false,
      "followers_count": 45,
      "friends_count": 131,
      "listed_count": 0,
      "created_at": "Wed Jan 30 06:57:24 +0000 2019",
      "favourites_count": 571,
      "utc_offset": null,
      "time_zone": null,
      "geo_enabled": false,
      "verified": false,
      "statuses_count": 465,
      "lang": null,
      "contributors_enabled": false,
      "is_translator": false,
      "is_translation_enabled": false,
      "profile_background_color": "F5F8FA",
      "profile_background_image_url": null,
      "profile_background_image_url_https": null,
      "profile_background_tile": false,
      "profile_image_url": "http://pbs.twimg.com/profile_images/1339466043090063360/KxrnQlAy_normal.jpg",
      "profile_image_url_https": "https://pbs.twimg.com/profile_images/1339466043090063360/KxrnQlAy_normal.jpg",
      "profile_banner_url": "https://pbs.twimg.com/profile_banners/1090504233428766720/1608188450",
      "profile_link_color": "1DA1F2",
      "profile_sidebar_border_color": "C0DEED",
      "profile_sidebar_fill_color": "DDEEF6",
      "profile_text_color": "333333",
      "profile_use_background_image": true,
      "has_extended_profile": true,
      "default_profile": true,
      "default_profile_image": false,
      "following": true,
      "follow_request_sent": false,
      "notifications": false,
      "translator_type": "none",
      "withheld_in_countries": []
    },
    "geo": null,
    "coordinates": null,
    "place": null,
    "contributors": null,
    "is_quote_status": false,
    "retweet_count": 0,
    "favorite_count": 3,
    "favorited": true,
    "retweeted": false,
    "lang": "en"
  },
  {
    "created_at": "Wed Jun 23 03:20:30 +0000 2021",
    "id": 1407539029520916500,
    "id_str": "1407539029520916480",
    "text": "psychological thrillers really the best movie genre 2me",
    "truncated": false,
    "entities": {
      "hashtags": [],
      "symbols": [],
      "user_mentions": [],
      "urls": []
    },
    "source": "<a href=\"http://twitter.com/download/iphone\" rel=\"nofollow\">Twitter for iPhone</a>",
    "in_reply_to_status_id": null,
    "in_reply_to_status_id_str": null,
    "in_reply_to_user_id": null,
    "in_reply_to_user_id_str": null,
    "in_reply_to_screen_name": null,
    "user": {
      "id": 3071524552,
      "id_str": "3071524552",
      "name": "CJ",
      "screen_name": "cdajewell",
      "location": "atl",
      "description": "",
      "url": "https://t.co/Z5TWbgVHnB",
      "entities": {
        "url": {
          "urls": [
            {
              "url": "https://t.co/Z5TWbgVHnB",
              "expanded_url": "http://instagram.com/cdajewell",
              "display_url": "instagram.com/cdajewell",
              "indices": [
                0,
                23
              ]
            }
          ]
        },
        "description": {
          "urls": []
        }
      },
      "protected": false,
      "followers_count": 36967,
      "friends_count": 790,
      "listed_count": 51,
      "created_at": "Thu Mar 05 03:16:04 +0000 2015",
      "favourites_count": 48380,
      "utc_offset": null,
      "time_zone": null,
      "geo_enabled": true,
      "verified": false,
      "statuses_count": 44075,
      "lang": null,
      "contributors_enabled": false,
      "is_translator": false,
      "is_translation_enabled": false,
      "profile_background_color": "C0DEED",
      "profile_background_image_url": "http://abs.twimg.com/images/themes/theme1/bg.png",
      "profile_background_image_url_https": "https://abs.twimg.com/images/themes/theme1/bg.png",
      "profile_background_tile": false,
      "profile_image_url": "http://pbs.twimg.com/profile_images/1404512797023735813/1ieEqBKw_normal.jpg",
      "profile_image_url_https": "https://pbs.twimg.com/profile_images/1404512797023735813/1ieEqBKw_normal.jpg",
      "profile_banner_url": "https://pbs.twimg.com/profile_banners/3071524552/1622045754",
      "profile_link_color": "1DA1F2",
      "profile_sidebar_border_color": "C0DEED",
      "profile_sidebar_fill_color": "DDEEF6",
      "profile_text_color": "333333",
      "profile_use_background_image": true,
      "has_extended_profile": true,
      "default_profile": true,
      "default_profile_image": false,
      "following": false,
      "follow_request_sent": false,
      "notifications": false,
      "translator_type": "none",
      "withheld_in_countries": []
    },
    "geo": null,
    "coordinates": null,
    "place": null,
    "contributors": null,
    "is_quote_status": false,
    "retweet_count": 11184,
    "favorite_count": 45931,
    "favorited": true,
    "retweeted": false,
    "lang": "en"
  },
  {
    "created_at": "Wed Jun 23 03:02:01 +0000 2021",
    "id": 1407534377802748000,
    "id_str": "1407534377802747912",
    "text": "shorty wearing a puffer jacket she’s anemic 🙋‍♀️",
    "truncated": false,
    "entities": {
      "hashtags": [],
      "symbols": [],
      "user_mentions": [],
      "urls": []
    },
    "source": "<a href=\"http://twitter.com/download/iphone\" rel=\"nofollow\">Twitter for iPhone</a>",
    "in_reply_to_status_id": null,
    "in_reply_to_status_id_str": null,
    "in_reply_to_user_id": null,
    "in_reply_to_user_id_str": null,
    "in_reply_to_screen_name": null,
    "user": {
      "id": 1430276449,
      "id_str": "1430276449",
      "name": "🪱✞",
      "screen_name": "ABVHVN",
      "location": "Los Angeles, CA",
      "description": "† † meet me at the end of the spiral & kiss me under the mushroom cloud ✶doomgen✶ 4 order inquiries no dms email abvhvn@gmail.com.  † https://t.co/0LGv0fZtmo",
      "url": "https://t.co/GS28hc2ZFK",
      "entities": {
        "url": {
          "urls": [
            {
              "url": "https://t.co/GS28hc2ZFK",
              "expanded_url": "http://abvhvn.com",
              "display_url": "abvhvn.com",
              "indices": [
                0,
                23
              ]
            }
          ]
        },
        "description": {
          "urls": [
            {
              "url": "https://t.co/0LGv0fZtmo",
              "expanded_url": "http://rarible.com/abvhvn",
              "display_url": "rarible.com/abvhvn",
              "indices": [
                134,
                157
              ]
            }
          ]
        }
      },
      "protected": false,
      "followers_count": 6081,
      "friends_count": 486,
      "listed_count": 13,
      "created_at": "Wed May 15 11:22:30 +0000 2013",
      "favourites_count": 54880,
      "utc_offset": null,
      "time_zone": null,
      "geo_enabled": true,
      "verified": false,
      "statuses_count": 19570,
      "lang": null,
      "contributors_enabled": false,
      "is_translator": false,
      "is_translation_enabled": false,
      "profile_background_color": "C0DEED",
      "profile_background_image_url": "http://abs.twimg.com/images/themes/theme1/bg.png",
      "profile_background_image_url_https": "https://abs.twimg.com/images/themes/theme1/bg.png",
      "profile_background_tile": false,
      "profile_image_url": "http://pbs.twimg.com/profile_images/1369796060902649856/PE-ZV_Bd_normal.jpg",
      "profile_image_url_https": "https://pbs.twimg.com/profile_images/1369796060902649856/PE-ZV_Bd_normal.jpg",
      "profile_banner_url": "https://pbs.twimg.com/profile_banners/1430276449/1623067561",
      "profile_link_color": "1DA1F2",
      "profile_sidebar_border_color": "C0DEED",
      "profile_sidebar_fill_color": "DDEEF6",
      "profile_text_color": "333333",
      "profile_use_background_image": true,
      "has_extended_profile": true,
      "default_profile": true,
      "default_profile_image": false,
      "following": true,
      "follow_request_sent": false,
      "notifications": false,
      "translator_type": "none",
      "withheld_in_countries": []
    },
    "geo": null,
    "coordinates": null,
    "place": null,
    "contributors": null,
    "is_quote_status": false,
    "retweet_count": 0,
    "favorite_count": 12,
    "favorited": true,
    "retweeted": false,
    "lang": "en"
  }
]