[
  {
    "artist": {
      "url": "https://www.last.fm/music/Good+Charlotte",
      "name": "Good Charlotte",
      "mbid": "b267ca80-034e-4dc1-9ed4-ec45f1fed41d"
    },
    "@attr": {
      "rank": "1"
    },
    "image": [
      {
        "size": "small",
        "#text": "https://lastfm.freetls.fastly.net/i/u/34s/8026b5bc7d9840499533d4fee7da1d5e.png"
      },
      {
        "size": "medium",
        "#text": "https://lastfm.freetls.fastly.net/i/u/64s/8026b5bc7d9840499533d4fee7da1d5e.png"
      },
      {
        "size": "large",
        "#text": "https://lastfm.freetls.fastly.net/i/u/174s/8026b5bc7d9840499533d4fee7da1d5e.png"
      },
      {
        "size": "extralarge",
        "#text": "https://lastfm.freetls.fastly.net/i/u/300x300/8026b5bc7d9840499533d4fee7da1d5e.png"
      }
    ],
    "playcount": "1",
    "url": "https://www.last.fm/music/Good+Charlotte/The+Young+and+the+Hopeless",
    "name": "The Young and the Hopeless",
    "mbid": "1e299415-55ef-466a-b096-5b71d158e06c"
  },
  {
    "artist": {
      "url": "https://www.last.fm/music/Katy+Perry",
      "name": "Katy Perry",
      "mbid": "122d63fc-8671-43e4-9752-34e846d62a9c"
    },
    "@attr": {
      "rank": "2"
    },
    "image": [
      {
        "size": "small",
        "#text": "https://lastfm.freetls.fastly.net/i/u/34s/37837a493636454d8ae5b6c36d705e21.jpg"
      },
      {
        "size": "medium",
        "#text": "https://lastfm.freetls.fastly.net/i/u/64s/37837a493636454d8ae5b6c36d705e21.jpg"
      },
      {
        "size": "large",
        "#text": "https://lastfm.freetls.fastly.net/i/u/174s/37837a493636454d8ae5b6c36d705e21.jpg"
      },
      {
        "size": "extralarge",
        "#text": "https://lastfm.freetls.fastly.net/i/u/300x300/37837a493636454d8ae5b6c36d705e21.jpg"
      }
    ],
    "playcount": "1",
    "url": "https://www.last.fm/music/Katy+Perry/Katy+Perry+-+Teenage+Dream:+The+Complete+Confection",
    "name": "Katy Perry - Teenage Dream: The Complete Confection",
    "mbid": ""
  }
]